[
  {
    "id": 1,
    "first_name": "Mirelle",
    "last_name": "Colebourn",
    "email": "mcolebourn0@hexun.com",
    "gender": "Female",
    "job_title": "GIS Technical Architect"
  },
  {
    "id": 2,
    "first_name": "Bili",
    "last_name": "Creak",
    "email": "bcreak1@ebay.co.uk",
    "gender": "Female",
    "job_title": "Senior Financial Analyst"
  },
  {
    "id": 3,
    "first_name": "Johnathan",
    "last_name": "Costa",
    "email": "jcosta2@yellowbook.com",
    "gender": "Male",
    "job_title": "Budget/Accounting Analyst IV"
  },
  {
    "id": 4,
    "first_name": "Eduardo",
    "last_name": "Rhoades",
    "email": "erhoades3@utexas.edu",
    "gender": "Male",
    "job_title": "Senior Developer"
  },
  {
    "id": 5,
    "first_name": "Carlos",
    "last_name": "Howerd",
    "email": "chowerd4@unicef.org",
    "gender": "Male",
    "job_title": "Human Resources Assistant I"
  },
  {
    "id": 6,
    "first_name": "Lucien",
    "last_name": "Kettridge",
    "email": "lkettridge5@addtoany.com",
    "gender": "Male",
    "job_title": "Health Coach III"
  },
  {
    "id": 7,
    "first_name": "Bron",
    "last_name": "Siggery",
    "email": "bsiggery6@amazonaws.com",
    "gender": "Male",
    "job_title": "Quality Control Specialist"
  },
  {
    "id": 8,
    "first_name": "Jessie",
    "last_name": "Frusher",
    "email": "jfrusher7@google.de",
    "gender": "Male",
    "job_title": "Legal Assistant"
  },
  {
    "id": 9,
    "first_name": "Baird",
    "last_name": "Yter",
    "email": "byter8@umn.edu",
    "gender": "Agender",
    "job_title": "Associate Professor"
  },
  {
    "id": 10,
    "first_name": "Dorie",
    "last_name": "Raccio",
    "email": "draccio9@google.fr",
    "gender": "Female",
    "job_title": "Teacher"
  },
  {
    "id": 11,
    "first_name": "Caleb",
    "last_name": "Gonneau",
    "email": "cgonneaua@biglobe.ne.jp",
    "gender": "Male",
    "job_title": "Civil Engineer"
  },
  {
    "id": 12,
    "first_name": "Carry",
    "last_name": "Habershaw",
    "email": "chabershawb@discuz.net",
    "gender": "Non-binary",
    "job_title": "Research Nurse"
  },
  {
    "id": 13,
    "first_name": "Carson",
    "last_name": "Teacy",
    "email": "cteacyc@nifty.com",
    "gender": "Male",
    "job_title": "Account Representative II"
  },
  {
    "id": 14,
    "first_name": "Roderigo",
    "last_name": "Greenlees",
    "email": "rgreenleesd@tripod.com",
    "gender": "Male",
    "job_title": "Clinical Specialist"
  },
  {
    "id": 15,
    "first_name": "Tabbatha",
    "last_name": "Ladloe",
    "email": "tladloee@spotify.com",
    "gender": "Female",
    "job_title": "Compensation Analyst"
  },
  {
    "id": 16,
    "first_name": "Mommy",
    "last_name": "McCuis",
    "email": "mmccuisf@amazonaws.com",
    "gender": "Female",
    "job_title": "Programmer III"
  },
  {
    "id": 17,
    "first_name": "Mallorie",
    "last_name": "Bartram",
    "email": "mbartramg@comcast.net",
    "gender": "Bigender",
    "job_title": "Design Engineer"
  },
  {
    "id": 18,
    "first_name": "Putnam",
    "last_name": "Peschmann",
    "email": "ppeschmannh@gravatar.com",
    "gender": "Male",
    "job_title": "Senior Developer"
  },
  {
    "id": 19,
    "first_name": "Davidde",
    "last_name": "MacAnulty",
    "email": "dmacanultyi@indiatimes.com",
    "gender": "Male",
    "job_title": "Programmer II"
  },
  {
    "id": 20,
    "first_name": "Florinda",
    "last_name": "Spriddle",
    "email": "fspriddlej@bloomberg.com",
    "gender": "Female",
    "job_title": "Automation Specialist I"
  },
  {
    "id": 21,
    "first_name": "Genovera",
    "last_name": "McFetridge",
    "email": "gmcfetridgek@devhub.com",
    "gender": "Female",
    "job_title": "Food Chemist"
  },
  {
    "id": 22,
    "first_name": "Lennard",
    "last_name": "Hedaux",
    "email": "lhedauxl@rakuten.co.jp",
    "gender": "Male",
    "job_title": "Executive Secretary"
  },
  {
    "id": 23,
    "first_name": "Man",
    "last_name": "Headley",
    "email": "mheadleym@hp.com",
    "gender": "Male",
    "job_title": "Registered Nurse"
  },
  {
    "id": 24,
    "first_name": "Lorraine",
    "last_name": "O'Bradden",
    "email": "lobraddenn@techcrunch.com",
    "gender": "Female",
    "job_title": "Office Assistant III"
  },
  {
    "id": 25,
    "first_name": "Jo",
    "last_name": "Tosney",
    "email": "jtosneyo@livejournal.com",
    "gender": "Male",
    "job_title": "Clinical Specialist"
  },
  {
    "id": 26,
    "first_name": "Marci",
    "last_name": "Dayley",
    "email": "mdayleyp@webnode.com",
    "gender": "Non-binary",
    "job_title": "Environmental Tech"
  },
  {
    "id": 27,
    "first_name": "Vivianna",
    "last_name": "Ruegg",
    "email": "vrueggq@yale.edu",
    "gender": "Female",
    "job_title": "Business Systems Development Analyst"
  },
  {
    "id": 28,
    "first_name": "Charla",
    "last_name": "Cruces",
    "email": "ccrucesr@deliciousdays.com",
    "gender": "Female",
    "job_title": "Information Systems Manager"
  },
  {
    "id": 29,
    "first_name": "Justinian",
    "last_name": "Kenson",
    "email": "jkensons@123-reg.co.uk",
    "gender": "Male",
    "job_title": "Registered Nurse"
  },
  {
    "id": 30,
    "first_name": "Juli",
    "last_name": "O'Daly",
    "email": "jodalyt@cyberchimps.com",
    "gender": "Female",
    "job_title": "Sales Representative"
  },
  {
    "id": 31,
    "first_name": "Catlaina",
    "last_name": "Neeves",
    "email": "cneevesu@github.com",
    "gender": "Non-binary",
    "job_title": "Occupational Therapist"
  },
  {
    "id": 32,
    "first_name": "Merry",
    "last_name": "Corwin",
    "email": "mcorwinv@prnewswire.com",
    "gender": "Female",
    "job_title": "GIS Technical Architect"
  },
  {
    "id": 33,
    "first_name": "Tildy",
    "last_name": "Chitson",
    "email": "tchitsonw@state.tx.us",
    "gender": "Female",
    "job_title": "Programmer Analyst I"
  },
  {
    "id": 34,
    "first_name": "Kelbee",
    "last_name": "Muehle",
    "email": "kmuehlex@ucoz.ru",
    "gender": "Male",
    "job_title": "Compensation Analyst"
  },
  {
    "id": 35,
    "first_name": "Rockey",
    "last_name": "Draco",
    "email": "rdracoy@virginia.edu",
    "gender": "Agender",
    "job_title": "Account Representative II"
  },
  {
    "id": 36,
    "first_name": "Kearney",
    "last_name": "Spicer",
    "email": "kspicerz@histats.com",
    "gender": "Male",
    "job_title": "Account Executive"
  },
  {
    "id": 37,
    "first_name": "Carma",
    "last_name": "Biskupek",
    "email": "cbiskupek10@scribd.com",
    "gender": "Female",
    "job_title": "Clinical Specialist"
  },
  {
    "id": 38,
    "first_name": "Skipper",
    "last_name": "Nuschke",
    "email": "snuschke11@oakley.com",
    "gender": "Male",
    "job_title": "Community Outreach Specialist"
  },
  {
    "id": 39,
    "first_name": "Gratia",
    "last_name": "Sheehy",
    "email": "gsheehy12@nyu.edu",
    "gender": "Bigender",
    "job_title": "Marketing Assistant"
  },
  {
    "id": 40,
    "first_name": "Kincaid",
    "last_name": "McKune",
    "email": "kmckune13@com.com",
    "gender": "Male",
    "job_title": "Legal Assistant"
  },
  {
    "id": 41,
    "first_name": "Keslie",
    "last_name": "Bidmead",
    "email": "kbidmead14@ycombinator.com",
    "gender": "Female",
    "job_title": "Food Chemist"
  },
  {
    "id": 42,
    "first_name": "Linzy",
    "last_name": "Wrightson",
    "email": "lwrightson15@issuu.com",
    "gender": "Female",
    "job_title": "Executive Secretary"
  },
  {
    "id": 43,
    "first_name": "Nicolle",
    "last_name": "Dana",
    "email": "ndana16@shinystat.com",
    "gender": "Female",
    "job_title": "Nurse"
  },
  {
    "id": 44,
    "first_name": "Darrick",
    "last_name": "Bernakiewicz",
    "email": "dbernakiewicz17@independent.co.uk",
    "gender": "Male",
    "job_title": "Librarian"
  },
  {
    "id": 45,
    "first_name": "Cos",
    "last_name": "Penni",
    "email": "cpenni18@wisc.edu",
    "gender": "Male",
    "job_title": "Senior Quality Engineer"
  },
  {
    "id": 46,
    "first_name": "Elna",
    "last_name": "Golley",
    "email": "egolley19@opensource.org",
    "gender": "Female",
    "job_title": "Pharmacist"
  },
  {
    "id": 47,
    "first_name": "Toiboid",
    "last_name": "Newis",
    "email": "tnewis1a@mac.com",
    "gender": "Male",
    "job_title": "Help Desk Operator"
  },
  {
    "id": 48,
    "first_name": "Dugald",
    "last_name": "Foucher",
    "email": "dfoucher1b@icio.us",
    "gender": "Male",
    "job_title": "Staff Scientist"
  },
  {
    "id": 49,
    "first_name": "Krissie",
    "last_name": "Dubber",
    "email": "kdubber1c@e-recht24.de",
    "gender": "Female",
    "job_title": "Web Developer IV"
  },
  {
    "id": 50,
    "first_name": "Field",
    "last_name": "Monkhouse",
    "email": "fmonkhouse1d@pinterest.com",
    "gender": "Male",
    "job_title": "Automation Specialist III"
  },
  {
    "id": 51,
    "first_name": "Gina",
    "last_name": "Bilton",
    "email": "gbilton1e@princeton.edu",
    "gender": "Female",
    "job_title": "Product Engineer"
  },
  {
    "id": 52,
    "first_name": "Jens",
    "last_name": "Marmyon",
    "email": "jmarmyon1f@t.co",
    "gender": "Male",
    "job_title": "Analyst Programmer"
  },
  {
    "id": 53,
    "first_name": "Loraine",
    "last_name": "Acors",
    "email": "lacors1g@cbc.ca",
    "gender": "Female",
    "job_title": "Accounting Assistant III"
  },
  {
    "id": 54,
    "first_name": "Madalena",
    "last_name": "Podbury",
    "email": "mpodbury1h@sogou.com",
    "gender": "Female",
    "job_title": "Information Systems Manager"
  },
  {
    "id": 55,
    "first_name": "Damiano",
    "last_name": "Gourley",
    "email": "dgourley1i@wikimedia.org",
    "gender": "Male",
    "job_title": "Desktop Support Technician"
  },
  {
    "id": 56,
    "first_name": "Padraic",
    "last_name": "Deddum",
    "email": "pdeddum1j@upenn.edu",
    "gender": "Male",
    "job_title": "Nurse Practicioner"
  },
  {
    "id": 57,
    "first_name": "Bree",
    "last_name": "Shannahan",
    "email": "bshannahan1k@webs.com",
    "gender": "Female",
    "job_title": "Account Representative II"
  },
  {
    "id": 58,
    "first_name": "Dion",
    "last_name": "Knoller",
    "email": "dknoller1l@people.com.cn",
    "gender": "Male",
    "job_title": "Assistant Professor"
  },
  {
    "id": 59,
    "first_name": "Malorie",
    "last_name": "Rembaud",
    "email": "mrembaud1m@hubpages.com",
    "gender": "Female",
    "job_title": "Safety Technician IV"
  },
  {
    "id": 60,
    "first_name": "Gillie",
    "last_name": "Bourgour",
    "email": "gbourgour1n@bandcamp.com",
    "gender": "Female",
    "job_title": "Programmer III"
  },
  {
    "id": 61,
    "first_name": "Alfredo",
    "last_name": "Walesby",
    "email": "awalesby1o@sakura.ne.jp",
    "gender": "Male",
    "job_title": "Senior Editor"
  },
  {
    "id": 62,
    "first_name": "Haslett",
    "last_name": "Juschke",
    "email": "hjuschke1p@earthlink.net",
    "gender": "Male",
    "job_title": "VP Product Management"
  },
  {
    "id": 63,
    "first_name": "Rosalynd",
    "last_name": "Cruess",
    "email": "rcruess1q@uiuc.edu",
    "gender": "Genderqueer",
    "job_title": "Registered Nurse"
  },
  {
    "id": 64,
    "first_name": "Vivianna",
    "last_name": "Mewett",
    "email": "vmewett1r@yellowbook.com",
    "gender": "Female",
    "job_title": "Quality Control Specialist"
  },
  {
    "id": 65,
    "first_name": "Natasha",
    "last_name": "Andrick",
    "email": "nandrick1s@hc360.com",
    "gender": "Non-binary",
    "job_title": "Marketing Manager"
  },
  {
    "id": 66,
    "first_name": "Martha",
    "last_name": "Dalzell",
    "email": "mdalzell1t@rambler.ru",
    "gender": "Female",
    "job_title": "Programmer I"
  },
  {
    "id": 67,
    "first_name": "Rory",
    "last_name": "Orwin",
    "email": "rorwin1u@1und1.de",
    "gender": "Female",
    "job_title": "Editor"
  },
  {
    "id": 68,
    "first_name": "Aura",
    "last_name": "Pirson",
    "email": "apirson1v@arizona.edu",
    "gender": "Female",
    "job_title": "Senior Quality Engineer"
  },
  {
    "id": 69,
    "first_name": "Duffy",
    "last_name": "Crathern",
    "email": "dcrathern1w@sourceforge.net",
    "gender": "Male",
    "job_title": "Compensation Analyst"
  },
  {
    "id": 70,
    "first_name": "Trix",
    "last_name": "Royan",
    "email": "troyan1x@vinaora.com",
    "gender": "Female",
    "job_title": "Teacher"
  },
  {
    "id": 71,
    "first_name": "Celene",
    "last_name": "Zanetto",
    "email": "czanetto1y@constantcontact.com",
    "gender": "Female",
    "job_title": "Automation Specialist IV"
  },
  {
    "id": 72,
    "first_name": "Barnie",
    "last_name": "Grenville",
    "email": "bgrenville1z@china.com.cn",
    "gender": "Male",
    "job_title": "Graphic Designer"
  },
  {
    "id": 73,
    "first_name": "Melina",
    "last_name": "Krishtopaittis",
    "email": "mkrishtopaittis20@nps.gov",
    "gender": "Female",
    "job_title": "Statistician II"
  },
  {
    "id": 74,
    "first_name": "Antonio",
    "last_name": "Laingmaid",
    "email": "alaingmaid21@xinhuanet.com",
    "gender": "Male",
    "job_title": "Senior Financial Analyst"
  },
  {
    "id": 75,
    "first_name": "Hally",
    "last_name": "Menilove",
    "email": "hmenilove22@springer.com",
    "gender": "Female",
    "job_title": "Civil Engineer"
  },
  {
    "id": 76,
    "first_name": "Moss",
    "last_name": "Haswall",
    "email": "mhaswall23@psu.edu",
    "gender": "Male",
    "job_title": "Nuclear Power Engineer"
  },
  {
    "id": 77,
    "first_name": "Hobie",
    "last_name": "Penwright",
    "email": "hpenwright24@sciencedirect.com",
    "gender": "Male",
    "job_title": "VP Accounting"
  },
  {
    "id": 78,
    "first_name": "Eachelle",
    "last_name": "Rammell",
    "email": "erammell25@apple.com",
    "gender": "Female",
    "job_title": "Internal Auditor"
  },
  {
    "id": 79,
    "first_name": "Gabby",
    "last_name": "Bercevelo",
    "email": "gbercevelo26@time.com",
    "gender": "Male",
    "job_title": "Environmental Tech"
  },
  {
    "id": 80,
    "first_name": "Josefina",
    "last_name": "Malia",
    "email": "jmalia27@altervista.org",
    "gender": "Female",
    "job_title": "Chemical Engineer"
  },
  {
    "id": 81,
    "first_name": "Rudd",
    "last_name": "Peiser",
    "email": "rpeiser28@desdev.cn",
    "gender": "Polygender",
    "job_title": "Administrative Assistant III"
  },
  {
    "id": 82,
    "first_name": "Rosana",
    "last_name": "Whacket",
    "email": "rwhacket29@economist.com",
    "gender": "Female",
    "job_title": "Quality Control Specialist"
  },
  {
    "id": 83,
    "first_name": "Halli",
    "last_name": "Tsar",
    "email": "htsar2a@noaa.gov",
    "gender": "Female",
    "job_title": "Structural Analysis Engineer"
  },
  {
    "id": 84,
    "first_name": "Lynett",
    "last_name": "Bourgaize",
    "email": "lbourgaize2b@tamu.edu",
    "gender": "Female",
    "job_title": "Database Administrator IV"
  },
  {
    "id": 85,
    "first_name": "Urbanus",
    "last_name": "Edgecumbe",
    "email": "uedgecumbe2c@moonfruit.com",
    "gender": "Male",
    "job_title": "Administrative Officer"
  },
  {
    "id": 86,
    "first_name": "Teressa",
    "last_name": "Birtwistle",
    "email": "tbirtwistle2d@facebook.com",
    "gender": "Female",
    "job_title": "Engineer III"
  },
  {
    "id": 87,
    "first_name": "Nappie",
    "last_name": "Gulliver",
    "email": "ngulliver2e@cargocollective.com",
    "gender": "Male",
    "job_title": "General Manager"
  },
  {
    "id": 88,
    "first_name": "Cobby",
    "last_name": "Greatbach",
    "email": "cgreatbach2f@dyndns.org",
    "gender": "Male",
    "job_title": "Senior Quality Engineer"
  },
  {
    "id": 89,
    "first_name": "Titos",
    "last_name": "Flippen",
    "email": "tflippen2g@examiner.com",
    "gender": "Male",
    "job_title": "Recruiting Manager"
  },
  {
    "id": 90,
    "first_name": "Micki",
    "last_name": "Frederick",
    "email": "mfrederick2h@prnewswire.com",
    "gender": "Female",
    "job_title": "Compensation Analyst"
  },
  {
    "id": 91,
    "first_name": "Brandise",
    "last_name": "Spykins",
    "email": "bspykins2i@ycombinator.com",
    "gender": "Female",
    "job_title": "Technical Writer"
  },
  {
    "id": 92,
    "first_name": "Kaine",
    "last_name": "Masser",
    "email": "kmasser2j@virginia.edu",
    "gender": "Bigender",
    "job_title": "Legal Assistant"
  },
  {
    "id": 93,
    "first_name": "Martynne",
    "last_name": "Gerish",
    "email": "mgerish2k@ca.gov",
    "gender": "Genderqueer",
    "job_title": "Biostatistician II"
  },
  {
    "id": 94,
    "first_name": "Ware",
    "last_name": "De Lorenzo",
    "email": "wdelorenzo2l@topsy.com",
    "gender": "Male",
    "job_title": "Financial Advisor"
  },
  {
    "id": 95,
    "first_name": "Bartram",
    "last_name": "Attride",
    "email": "battride2m@shutterfly.com",
    "gender": "Male",
    "job_title": "Software Test Engineer IV"
  },
  {
    "id": 96,
    "first_name": "Greggory",
    "last_name": "Malyj",
    "email": "gmalyj2n@cnbc.com",
    "gender": "Male",
    "job_title": "Civil Engineer"
  },
  {
    "id": 97,
    "first_name": "Dene",
    "last_name": "Brisseau",
    "email": "dbrisseau2o@thetimes.co.uk",
    "gender": "Male",
    "job_title": "Database Administrator I"
  },
  {
    "id": 98,
    "first_name": "Xenos",
    "last_name": "Allwright",
    "email": "xallwright2p@umn.edu",
    "gender": "Male",
    "job_title": "Programmer III"
  },
  {
    "id": 99,
    "first_name": "Arvin",
    "last_name": "Paz",
    "email": "apaz2q@washington.edu",
    "gender": "Male",
    "job_title": "Analog Circuit Design manager"
  },
  {
    "id": 100,
    "first_name": "Stern",
    "last_name": "Deadman",
    "email": "sdeadman2r@t.co",
    "gender": "Male",
    "job_title": "Registered Nurse"
  },
  {
    "first_name": "Roni",
    "last_name": "pradhan",
    "email": "rvvats@gmail.com",
    "job_title": "DevOps engineer",
    "id": 101
  },
  {
    "first_name": "kanha",
    "last_name": "choubhey",
    "email": "rvvats9090@gmail.com",
    "job_title": "Software engineer",
    "id": 102
  },
  {
    "first_name": "Roni",
    "last_name": "pradhan",
    "gender": "male",
    "email": "ronikiller3@gmail.com",
    "id": 103,
    "job_title": "Software engineer"
  }
]
